navigate_mmcore_plugin/VERSION
navigate_mmcore_plugin/__init__.py
navigate_mmcore_plugin/plugin_config.yml
navigate_mmcore_plugin/controller/__init__.py
navigate_mmcore_plugin/controller/mmcore_plugin_controller.py
navigate_mmcore_plugin/model/__init__.py
navigate_mmcore_plugin/model/devices/__init__.py
navigate_mmcore_plugin/model/devices/plugin_device/__init__.py
navigate_mmcore_plugin/model/devices/plugin_device/device_startup_functions.py
navigate_mmcore_plugin/model/devices/plugin_device/shutter_device.py
navigate_mmcore_plugin/model/devices/plugin_device/stage_device.py
navigate_mmcore_plugin/view/__init__.py
navigate_mmcore_plugin/view/mmcore_plugin_frame.py
navigate_mmcore_plugin-0.0.1.dist-info/LICENSE
navigate_mmcore_plugin-0.0.1.dist-info/METADATA
navigate_mmcore_plugin-0.0.1.dist-info/WHEEL
navigate_mmcore_plugin-0.0.1.dist-info/entry_points.txt
navigate_mmcore_plugin-0.0.1.dist-info/top_level.txt
navigate_mmcore_plugin-0.0.1.dist-info/RECORD
