Metadata-Version: 2.1
Name: navigate-mmcore-plugin
Version: 0.0.1
Summary: A plugin for access to Micro-Manager devices from within navigate.
Author: The Dean Lab, UT Southwestern Medical Center
Project-URL: Source, https://github.com/TheDeanLab/navigate-mmcore-plugin
Classifier: Intended Audience :: Developers
Classifier: Operating System :: POSIX :: Linux
Classifier: Operating System :: MacOS :: MacOS X
Classifier: Operating System :: Microsoft :: Windows
Classifier: Programming Language :: Python :: 3.9
Classifier: Programming Language :: Python :: Implementation :: CPython
Classifier: Programming Language :: Python :: Implementation :: PyPy
Requires-Python: >=3.9.7
License-File: LICENSE
Requires-Dist: pymmcore
Provides-Extra: dev
Requires-Dist: pytest ; extra == 'dev'
Requires-Dist: pytest-xvfb ; extra == 'dev'
Requires-Dist: pytest-cov ; extra == 'dev'
Requires-Dist: pre-commit ; extra == 'dev'
Provides-Extra: docs
Requires-Dist: numpydoc ; extra == 'docs'
Requires-Dist: nbconvert ; extra == 'docs'
Requires-Dist: sphinx <6.0.0 ; extra == 'docs'
Requires-Dist: sphinx-rtd-theme ; extra == 'docs'
Requires-Dist: sphinx-copybutton ; extra == 'docs'
Requires-Dist: sphinx-issues ; extra == 'docs'
Requires-Dist: sphinx-design ; extra == 'docs'
Requires-Dist: pyyaml ; extra == 'docs'
Requires-Dist: pydata-sphinx-theme ==0.10.0rc2 ; extra == 'docs'
Requires-Dist: sphinx-toolbox ; extra == 'docs'
